django_shells-0.1.0.dist-info/DESCRIPTION.rst
django_shells-0.1.0.dist-info/METADATA
django_shells-0.1.0.dist-info/RECORD
django_shells-0.1.0.dist-info/WHEEL
django_shells-0.1.0.dist-info/metadata.json
django_shells-0.1.0.dist-info/top_level.txt
shells/__init__.py
shells/models.py
shells/management/__init__.py
shells/management/commands/__init__.py
shells/management/commands/dbshell.py
shells/management/commands/shell.py
