Metadata-Version: 2.0
Name: django-shells
Version: 0.1.0
Summary: Better shells for your manage.py
Home-page: https://github.com/uranusjr/django-shells
Author: Tzu-ping Chung
Author-email: uranusjr@gmail.com
License: BSD
Keywords: django-shells
Platform: UNKNOWN
Classifier: Development Status :: 3 - Alpha
Classifier: Framework :: Django
Classifier: Framework :: Django :: 1.8
Classifier: Intended Audience :: Developers
Classifier: License :: OSI Approved :: BSD License
Classifier: Natural Language :: English
Classifier: Programming Language :: Python :: 2
Classifier: Programming Language :: Python :: 2.7
Classifier: Programming Language :: Python :: 3
Classifier: Programming Language :: Python :: 3.3
Classifier: Programming Language :: Python :: 3.4
Classifier: Programming Language :: Python :: 3.5
